insee_sirene/__init__.py
insee_sirene/admin.py
insee_sirene/apps.py
insee_sirene/conf/__init__.py
insee_sirene/conf/settings.py
insee_sirene/constants.py
insee_sirene/forms.py
insee_sirene/history/README.md
insee_sirene/history/raw_generated_models.py
insee_sirene/management/commands/download_insee_sirene_csv_files.py
insee_sirene/management/commands/generate_insee_sirene_models.py
insee_sirene/management/commands/import_insee_sirene.py
insee_sirene/migrations/0001_initial.py
insee_sirene/migrations/0002_alter_etablissement_etablissement_siege.py
insee_sirene/migrations/__init__.py
insee_sirene/models.py
insee_sirene/shortcuts.py
insee_sirene/urls.py
insee_sirene/views.py
django_insee_sirene-0.0.4.dist-info/AUTHORS.md
django_insee_sirene-0.0.4.dist-info/LICENSE
django_insee_sirene-0.0.4.dist-info/METADATA
django_insee_sirene-0.0.4.dist-info/WHEEL
django_insee_sirene-0.0.4.dist-info/RECORD
