Metadata-Version: 2.1
Name: django-insee-sirene
Version: 0.0.4
Summary: Integrate INSEE Sirene v3 database in Django project
Home-page: https://gitlab.com/kapt/open-source/django-insee-sirene
License: GNU GPLv3
Author: Kapt dev team
Author-email: dev@kapt.mobi
Requires-Python: ==3.12.*
Classifier: License :: Other/Proprietary License
Classifier: Programming Language :: Python :: 3
Classifier: Programming Language :: Python :: 3.12
Requires-Dist: django (>=4.2,<4.3)
Requires-Dist: requests (>=2.31.0,<3.0.0)
Project-URL: Repository, https://gitlab.com/kapt/open-source/django-insee-sirene
